[
  {
    "id": "shiroka_laka",
    "name": "Shiroka Laka",
    "region": "Rhodopes",
    "lat": 41.7333,
    "lng": 24.6167,
    "population": 400,
    "altitude_m": 1000,
    "description": "A village famous for its bagpipe school and traditional Rhodope architecture. Stone houses line cobbled streets unchanged for 200 years.",
    "tags": ["music", "tradition", "architecture", "rhodopes"],
    "cws_base": 42,
    "cluster_id": "rhodopes_south"
  },
  {
    "id": "kovachevitsa",
    "name": "Kovachevitsa",
    "region": "Rhodopes",
    "lat": 41.7667,
    "lng": 23.9333,
    "population": 60,
    "altitude_m": 720,
    "description": "One of Bulgaria's most preserved medieval villages. Fortress-like stone houses, no cars allowed inside. Time stands still here.",
    "tags": ["medieval", "architecture", "heritage", "quiet"],
    "cws_base": 38,
    "cluster_id": "rhodopes_west"
  },
  {
    "id": "leshten",
    "name": "Leshten",
    "region": "Rhodopes",
    "lat": 41.7500,
    "lng": 23.9000,
    "population": 30,
    "altitude_m": 810,
    "description": "A tiny Rhodope hamlet with panoramic views over the valley. Restored stone guesthouses, wild herb gathering, and total silence.",
    "tags": ["panorama", "nature", "solitude", "herbs"],
    "cws_base": 29,
    "cluster_id": "rhodopes_west"
  },
  {
    "id": "bozhentsi",
    "name": "Bozhentsi",
    "region": "Central Balkans",
    "lat": 42.8667,
    "lng": 25.3833,
    "population": 120,
    "altitude_m": 600,
    "description": "An architectural reserve in the Balkan foothills. Icon painting, rose oil production, national revival-era stone houses.",
    "tags": ["crafts", "icons", "revival", "balkans"],
    "cws_base": 51,
    "cluster_id": "balkans_central"
  },
  {
    "id": "zheravna",
    "name": "Zheravna",
    "region": "Eastern Balkans",
    "lat": 42.8500,
    "lng": 26.4333,
    "population": 200,
    "altitude_m": 580,
    "description": "Bulgaria's largest architectural reserve. Chestnut forests, water mills, authentic taverns. Inspiration for Yordan Yovkov's literature.",
    "tags": ["literary", "history", "forest", "mills"],
    "cws_base": 47,
    "cluster_id": "balkans_east"
  },
  {
    "id": "koprivshtitsa",
    "name": "Koprivshtitsa",
    "region": "Central Balkans",
    "lat": 42.6333,
    "lng": 24.3333,
    "population": 2500,
    "altitude_m": 1060,
    "description": "The town that sparked the April Uprising of 1876. A living museum of Bulgarian history with six house-museums and colorful facades.",
    "tags": ["uprising", "history", "museums", "april"],
    "cws_base": 65,
    "cluster_id": "balkans_central"
  },
  {
    "id": "melnik",
    "name": "Melnik",
    "region": "Southwest",
    "lat": 41.5167,
    "lng": 23.3833,
    "population": 180,
    "altitude_m": 440,
    "description": "Bulgaria's smallest town. Famous for Melnik wine and unique sand pyramids. Thracian, Greek, and Bulgarian layers of history.",
    "tags": ["wine", "pyramids", "thracian", "southwest"],
    "cws_base": 58,
    "cluster_id": "southwest"
  },
  {
    "id": "tryavna",
    "name": "Tryavna",
    "region": "Central Balkans",
    "lat": 42.8667,
    "lng": 25.5000,
    "population": 8000,
    "altitude_m": 380,
    "description": "The capital of Bulgarian wood carving. The Tryavna school produced master craftsmen whose work fills monasteries across Bulgaria.",
    "tags": ["woodcarving", "crafts", "school", "balkans"],
    "cws_base": 55,
    "cluster_id": "balkans_central"
  },
  {
    "id": "stoilovo",
    "name": "Stoilovo",
    "region": "Strandzha",
    "lat": 42.0333,
    "lng": 27.5833,
    "population": 50,
    "altitude_m": 280,
    "description": "Deep in the ancient Strandzha forest. The last village practicing Nestinarstvo — fire-walking on live coals, a UNESCO-recognized tradition.",
    "tags": ["nestinarstvo", "firewalking", "strandzha", "unesco"],
    "cws_base": 22,
    "cluster_id": "strandzha"
  },
  {
    "id": "teteven",
    "name": "Teteven",
    "region": "Balkan Foothills",
    "lat": 42.9167,
    "lng": 24.2667,
    "altitude_m": 520,
    "population": 9000,
    "description": "Gateway to Teteven Balkan. Rock formations, waterfalls, and a bear sanctuary nearby. Hayduk history and traditional yogurt culture.",
    "tags": ["hiking", "waterfalls", "bears", "hayduk"],
    "cws_base": 44,
    "cluster_id": "balkans_central"
  }
]
